{
  "Medium": "Chrome-plated tubular steel and velvet", 
  "Dimensions": "33 x 21 5/8 x 35 7/8\" (83.8 x 55 x 91.1 cm)", 
  "Classification": "A&D Design", 
  "CreditLine": "Gift of Knoll International, Inc.", 
  "URL": "http://www.moma.org/collection/works/3224", 
  "ImageURL": "http://www.moma.org/media/W1siZiIsIjIyOTIxMSJdLFsicCIsImNvbnZlcnQiLCItcmVzaXplIDIwMDB4MjAwMD4iXV0?sha=c2de42661ccab580", 
  "Artist": "Ludwig Mies van der Rohe", 
  "Date": "1931", 
  "Keywords": [
    "Ludwig Mies van der Rohe", 
    "MR Lounge Chair (model 34)", 
    "1931"
  ], 
  "ArtistID": 7166, 
  "Title": "MR Lounge Chair (model 34)", 
  "Department": "Architecture & Design", 
  "MoMANumber": "297.1976", 
  "DateAcquired": "1976-10-22", 
  "ArtistBio": "(American, born Germany. 1886\u20131969)", 
  "CuratorApproved": "Y", 
  "ObjectID": "3224"
}