{
  "Medium": "Ink, colored ink, and lithograph on four pieces of paper", 
  "Dimensions": "(.a): 14 7/8 \u00d7 20\" (37.8 \u00d7 50.8 cm); (.b): 15 1/8 \u00d7 20\" (38.4 \u00d7 50.8 cm); (.c): 15 1/8 \u00d7 20\" (38.4 \u00d7 50.8 cm); (.d): 15 \u00d7 20\" (38.1 \u00d7 50.8 cm)", 
  "Classification": "Drawing", 
  "CreditLine": "Gift of Samuel I. Rosenman (by exchange)", 
  "URL": "http://www.moma.org/collection/works/33475", 
  "ImageURL": null, 
  "Artist": "Marcel Broodthaers", 
  "Date": "1973", 
  "Keywords": [
    "Marcel Broodthaers", 
    "Journal d'un voyage utopique", 
    "1973"
  ], 
  "ArtistID": 795, 
  "Title": "Journal d'un voyage utopique", 
  "Department": "Drawings", 
  "MoMANumber": "42.1985.a-d", 
  "DateAcquired": "1985-03-08", 
  "ArtistBio": "(Belgian, 1924\u20131976)", 
  "CuratorApproved": "Y", 
  "ObjectID": "33475"
}