{
  "Medium": "Ink, pencil, and gouache on paper", 
  "Dimensions": "5 3/4 x 3 3/8\" (14.6 x 8.6 cm)", 
  "Classification": "Drawing", 
  "Artist": "Jean Dubuffet", 
  "URL": "http://www.moma.org/collection/works/85112", 
  "CreditLine": "Gift of the artist", 
  "DateAcquired": "1968-10-10", 
  "Department": "Drawings", 
  "Title": "Sketchbook: El Golea, II", 
  "MoMANumber": "1333.1968.24", 
  "Date": "1948", 
  "ArtistBio": "(French, 1901\u20131985)", 
  "CuratorApproved": "Y", 
  "ObjectID": "85112"
}