{
  "Medium": "Linoleum cut, printed in black", 
  "Dimensions": "composition  9 11/16 x 6 15/16\" (24.6 x 17.6 cm)", 
  "Classification": "Illustrated Book", 
  "Artist": "Henri Matisse", 
  "URL": "", 
  "CuratorApproved": "N", 
  "Title": "5th variant of ...ONE WOULD SAY THAT SHE NEVER SAW ME... (volume II, folio 30) from PASIPHA\u00c9", 
  "DateAcquired": "1982-05-05", 
  "Date": "1943-1981", 
  "Department": "Prints & Illustrated Books", 
  "MoMANumber": "148.1982.B25", 
  "ArtistBio": "French, 1869\u20131954", 
  "CreditLine": "Gift of The Heirs of Henri Matisse", 
  "ObjectID": "11870"
}