{
  "Medium": "Etching, soft ground etching, and lift ground aquatint, printed in black", 
  "Dimensions": "plate  2 7/8 x 7 1/2\" (7.3 x 19.1 cm)", 
  "Classification": "Illustrated Book", 
  "Artist": "Jasper Johns", 
  "URL": "", 
  "CreditLine": "Gift of Celeste and Armand Bartos (in perpetuity)", 
  "DateAcquired": "1978-05-22", 
  "Department": "Prints & Illustrated Books", 
  "Title": "FOUR PANELS (DABC) (headpiece, folio 14) from FOIRADES/FIZZLES", 
  "MoMANumber": "454.1978.6", 
  "Date": "1975-1976", 
  "ArtistBio": "(American, born 1930)", 
  "CuratorApproved": "N", 
  "ObjectID": "17386"
}