{
  "Medium": "Gelatin silver print, printed 1979", 
  "Dimensions": "11 x 14\" (28 x 35.6 cm)", 
  "Classification": "Photograph", 
  "CreditLine": "Gift of Mr. and Mrs. James Hunter", 
  "URL": "", 
  "ImageURL": null, 
  "Artist": "Danny Lyon", 
  "Date": "1966", 
  "Department": "Photography", 
  "Title": "Crossing the Ohio, Louisville", 
  "MoMANumber": "412.1992.10", 
  "DateAcquired": "1992-10-15", 
  "ArtistBio": "(American, born 1942)", 
  "CuratorApproved": "N", 
  "ObjectID": "52907"
}