{
  "Medium": "Screenprint, with hand additions", 
  "Dimensions": "sheet: 22 3/8 \u00d7 15 3/4\" (56.8 \u00d7 40 cm)", 
  "Classification": "Print", 
  "CreditLine": "Gift of the artist", 
  "URL": "", 
  "ImageURL": null, 
  "Artist": "Louise Bourgeois", 
  "Date": "2002", 
  "Department": "Prints & Illustrated Books", 
  "Title": "Untitled", 
  "MoMANumber": "1702.2008", 
  "DateAcquired": "2008-10-08", 
  "ArtistBio": "(American, born France. 1911\u20132010)", 
  "CuratorApproved": "N", 
  "ObjectID": "119731"
}