{
  "Medium": "Watercolor and pencil on paper", 
  "Dimensions": "22 1/4 x 30 1/8\" (56.5 x 76.5 cm)", 
  "Classification": "Drawing", 
  "CreditLine": "The Judith Rothschild Foundation Contemporary Drawings Collection Gift", 
  "URL": "http://www.moma.org/collection/works/97826", 
  "ImageURL": "http://www.moma.org/media/W1siZiIsIjEzNjgyOSJdLFsicCIsImNvbnZlcnQiLCItcmVzaXplIDIwMDB4MjAwMD4iXV0?sha=956e348fd5d4a689", 
  "Artist": "Joe Zucker", 
  "Date": "2003", 
  "Keywords": [
    "Joe Zucker", 
    "Robocrate Flagship", 
    "2003"
  ], 
  "ArtistID": 6588, 
  "Title": "Robocrate Flagship", 
  "Department": "Drawings", 
  "MoMANumber": "3487.2005", 
  "DateAcquired": "2005-05-10", 
  "ArtistBio": "(American, born 1941)", 
  "CuratorApproved": "Y", 
  "ObjectID": "97826"
}