{
  "Medium": "One from an illustrated book with forty-two photogravure and drypoints after celluloid engravings", 
  "Dimensions": "composition (irreg.): 2 1/2 x 2 11/16\" (6.3 x 6.8cm); page: 13 1/16 x 9 15/16\" (33.2 x 25.2 cm)", 
  "Classification": "Illustrated Book", 
  "Artist": "Salvador Dal\u00ed", 
  "URL": "http://www.moma.org/collection/works/23629", 
  "CuratorApproved": "Y", 
  "CreditLine": "The Louis E. Stern Collection", 
  "Date": "1934", 
  "Department": "Prints & Illustrated Books", 
  "MoMANumber": "771.1964.7", 
  "ArtistBio": "(Spanish, 1904\u20131989)", 
  "DateAcquired": "1964-10-06", 
  "\ufeffTitle": "Tailpiece (page 36) from Les Chants de Maldoror", 
  "ObjectID": "23629"
}