{
  "Medium": "Lithograph", 
  "Dimensions": "composition (irreg.): 18 7/8 x 15 3/16\" (48 x 38.5 cm); sheet: 22 1/16 x 16 7/8\" (56 x 42.9 cm)", 
  "Classification": "Print", 
  "Artist": "Pierre Alechinsky", 
  "URL": "http://www.moma.org/collection/works/71385", 
  "CreditLine": "Gift of the artist", 
  "DateAcquired": "1978-10-17", 
  "Keywords": [
    "Pierre Alechinsky", 
    "Circletude (Cerclitude) from the portfolio Pencil on Shell (Crayon sur coquille)", 
    "1971"
  ], 
  "ArtistID": 107, 
  "Title": "Circletude (Cerclitude) from the portfolio Pencil on Shell (Crayon sur coquille)", 
  "Department": "Prints & Illustrated Books", 
  "MoMANumber": "576.1978.9", 
  "Date": "1971", 
  "ArtistBio": "(Belgian, born 1927)", 
  "CuratorApproved": "Y", 
  "ObjectID": "71385"
}