{
  "Medium": "Molded plywood", 
  "Dimensions": "4 1/4 x 7 3/4 x 42\" (10.8 x 19.7 x 106.7 cm)", 
  "Classification": "A&D Design", 
  "Artist": "Charles Eames", 
  "URL": "http://www.moma.org/collection/works/4661", 
  "CuratorApproved": "Y", 
  "Title": "Leg Splint", 
  "DateAcquired": "2001-04-30", 
  "Date": "1942", 
  "ArtistID": 1671, 
  "Keywords": [
    "online art collection", 
    "Charles Eames and Ray Eames", 
    "Leg Splint", 
    "1942"
  ], 
  "Department": "Architecture & Design", 
  "MoMANumber": "1298.2001", 
  "ArtistBio": "American, 1907\u20131978", 
  "CreditLine": "Gift of the manufacturer", 
  "ObjectID": "4661"
}