{
  "Medium": "Artist's book", 
  "Dimensions": "Page: 11 7/16 x 7 11/16\" (29 x 19.5 cm)", 
  "Classification": "Illustrated Book", 
  "Artist": "A.R. Penck (Ralf Winkler)", 
  "URL": "http://www.moma.org/collection/works/9800", 
  "CreditLine": "Purchase", 
  "DateAcquired": "1982-01-21", 
  "Keywords": [
    "A,R", 
    "Penck (Ralf Winkler)", 
    "Standarts", 
    "1970"
  ], 
  "ArtistID": 4546, 
  "Title": "Standarts", 
  "Department": "Prints & Illustrated Books", 
  "MoMANumber": "24.1982", 
  "Date": "1970", 
  "ArtistBio": "(German, born 1939)", 
  "CuratorApproved": "Y", 
  "ObjectID": "9800"
}