{
  "Medium": "Lithograph", 
  "Dimensions": "", 
  "Classification": "Print", 
  "CreditLine": "Nina and Gordon Bunshaft Bequest", 
  "URL": "http://www.moma.org/collection/works/71387", 
  "ImageURL": null, 
  "Artist": "Henry Moore", 
  "Date": "1977", 
  "Keywords": [
    "Henry Moore", 
    "Stone Reclining Figure", 
    "(1977)"
  ], 
  "ArtistID": 4071, 
  "Title": "Stone Reclining Figure", 
  "Department": "Prints & Illustrated Books", 
  "MoMANumber": "576.1994", 
  "DateAcquired": "1994-11-08", 
  "ArtistBio": "(British, 1898\u20131986)", 
  "CuratorApproved": "Y", 
  "ObjectID": "71387"
}