{
  "Medium": "Gelatin silver print, printed 1963", 
  "Dimensions": "11 11/16 x 9\" (29.7 x 22.8 cm)", 
  "Classification": "Photograph", 
  "Artist": "Ansel Adams", 
  "URL": "", 
  "CuratorApproved": "N", 
  "CreditLine": "Gift of David H. McAlpin", 
  "Date": "c. 1962", 
  "Department": "Photography", 
  "MoMANumber": "1711.1968", 
  "ArtistBio": "(American, 1902\u20131984)", 
  "DateAcquired": "1968-05-01", 
  "\ufeffTitle": "Sierra Nevada, Winter Evening, from Owens Valley, California", 
  "ObjectID": "58294"
}