{
  "Medium": "Colored pencil on eleven pieces of  paper", 
  "Dimensions": "6 x 6\" (15.2 x 15.2 cm) each", 
  "Classification": "Drawing", 
  "Artist": "Mark Dion", 
  "URL": "http://www.moma.org/collection/works/169878", 
  "CuratorApproved": "Y", 
  "CreditLine": "Acquired through the generosity of the Contemporary Arts Council of The Museum of Modern Art", 
  "Date": "2011", 
  "Department": "Drawings", 
  "MoMANumber": "647.2013.a-k", 
  "ArtistBio": "(American, born 1961)", 
  "DateAcquired": "2013-05-23", 
  "\ufeffTitle": "Phantoms of the Clark Expedition", 
  "ObjectID": "169878"
}