{
  "Medium": "Photoetching and aquatint, with hand additions  ", 
  "Dimensions": "plate  8 7/8 x 8 7/8\" (22.5 x 22.5 cm)  irreg sheet  25 x 18 1/8\" (63.6 x 46.1 cm)", 
  "Classification": "Print", 
  "Artist": "Liliana Porter", 
  "URL": "http://www.moma.org/collection/works/60854", 
  "CuratorApproved": "Y", 
  "Title": "The Masterpiece on the Mysteries of the Horizon from the series Magritte", 
  "DateAcquired": "1977-02-10", 
  "Date": "1976", 
  "Department": "Prints & Illustrated Books", 
  "MoMANumber": "46.1977", 
  "ArtistBio": "Argentine, born 1941", 
  "CreditLine": "Latin American Fund", 
  "ObjectID": "60854"
}