{
  "Medium": "Etching, aquatint, and drypoint from a portfolio of fifty etching, aquatint and drypoints", 
  "Dimensions": "plate: 7 13/16 x 9 13/16\" (19.8 x 25 cm); sheet: 13 3/4 x 18 3/8\" (35 x 46.6 cm)", 
  "Classification": "Print", 
  "CreditLine": "Gift of Abby Aldrich Rockefeller", 
  "URL": "http://www.moma.org/collection/works/87759", 
  "ImageURL": "http://www.moma.org/media/W1siZiIsIjExNjQzNCJdLFsicCIsImNvbnZlcnQiLCItcmVzaXplIDIwMDB4MjAwMD4iXV0?sha=90505c9f24e18b9d", 
  "Artist": "Otto Dix", 
  "Date": "(1924)", 
  "Keywords": [
    "Otto Dix", 
    "Transporting the Wounded in Houthulst Forest (Verwundetentransport im Houthulster Wald) from The War (Der Krieg)", 
    "(1924)"
  ], 
  "ArtistID": 1559, 
  "Title": "Transporting the Wounded in Houthulst Forest (Verwundetentransport im Houthulster Wald) from The War (Der Krieg)", 
  "Department": "Prints & Illustrated Books", 
  "MoMANumber": "159.1934.47", 
  "DateAcquired": "1934-07-02", 
  "ArtistBio": "(German, 1891\u20131969)", 
  "CuratorApproved": "Y", 
  "ObjectID": "87759"
}