{
  "Medium": "Ink on paper", 
  "Dimensions": "11 5/8 x 16 1/2\" (29.5 x 41.9 cm)", 
  "Classification": "Drawing", 
  "Artist": "Billy Sullivan", 
  "URL": "http://www.moma.org/collection/works/97498", 
  "CuratorApproved": "Y", 
  "CreditLine": "The Judith Rothschild Foundation Contemporary Drawings Collection Gift", 
  "Date": "1997", 
  "ArtistID": 8377, 
  "Keywords": [
    "online art collection", 
    "Billy Sullivan", 
    "Untitled (VI)", 
    "1997"
  ], 
  "Department": "Drawings", 
  "MoMANumber": "3189.2005", 
  "ArtistBio": "(American, born 1946)", 
  "DateAcquired": "2005-05-10", 
  "\ufeffTitle": "Untitled (VI)", 
  "ObjectID": "97498"
}