{
  "Medium": "Gelatin silver print", 
  "Dimensions": "10 7/8 x 8 7/16\" (27.6 x 21.5 cm)", 
  "Classification": "Photograph", 
  "Artist": "Sameer Makarius", 
  "URL": "http://www.moma.org/collection/works/145261", 
  "CreditLine": "Latin American and Caribbean Fund through gift of Carlos and Gisela Padula", 
  "DateAcquired": "2011-05-07", 
  "Department": "Photography", 
  "Title": "Untitled", 
  "MoMANumber": "451.2011", 
  "Date": "1950s", 
  "ArtistBio": "(Argentine, born Egypt. 1924\u20132009)", 
  "CuratorApproved": "Y", 
  "ObjectID": "145261"
}