{
  "Medium": "Typewriting on carbon paper", 
  "Dimensions": "10 7/8 x 8 1/2\" (27.5 x 21.5 cm)", 
  "Classification": "Drawing", 
  "CreditLine": "Gift of Sarah-Ann and Werner H. Kramarsky", 
  "URL": "http://www.moma.org/collection/works/36758", 
  "ImageURL": "http://www.moma.org/media/W1siZiIsIjI2NzU5MSJdLFsicCIsImNvbnZlcnQiLCItcmVzaXplIDIwMDB4MjAwMD4iXV0?sha=844352e4eb64bc5b", 
  "Artist": "Allyson Strafella", 
  "Date": "(1995)", 
  "Keywords": [
    "Allyson Strafella", 
    "Untitled", 
    "(1995)"
  ], 
  "ArtistID": 8137, 
  "Title": "Untitled", 
  "Department": "Drawings", 
  "MoMANumber": "403.1999", 
  "DateAcquired": "1999-10-21", 
  "ArtistBio": "(American, born 1969)", 
  "CuratorApproved": "Y", 
  "ObjectID": "36758"
}