{
  "Medium": "Pencil on paper", 
  "Dimensions": "8 5/16 x 13\" (21.1 x 33 cm)", 
  "Classification": "A&D Mies van der Rohe Archive", 
  "Artist": "Ludwig Mies van der Rohe", 
  "URL": "http://www.moma.org/collection/works/106380", 
  "CuratorApproved": "Y", 
  "CreditLine": "Mies van der Rohe Archive, gift of the architect", 
  "Date": "1926-46", 
  "Department": "Architecture & Design", 
  "MoMANumber": "652.1974", 
  "ArtistBio": "(American, born Germany. 1886\u20131969)", 
  "DateAcquired": "1974-11-06", 
  "\ufeffTitle": "Lounge Chair with Arms. Lounge Chair without Arms. (Perspective and detail sketches)", 
  "ObjectID": "106380"
}