{
  "Medium": "Bone china", 
  "Dimensions": "Approx. h. 3 1/16 x diam. 2 9/16\" (7.7 x 6.5 cm)", 
  "Classification": "A&D Design", 
  "Artist": "Greg Lynn", 
  "URL": "http://www.moma.org/collection/works/105179", 
  "CreditLine": "Gift of the manufacturer", 
  "DateAcquired": "2006-10-03", 
  "Department": "Architecture & Design", 
  "Title": "Supple Cups", 
  "MoMANumber": "572.2006.1-2", 
  "Date": "2005", 
  "ArtistBio": "(American, born 1964)", 
  "CuratorApproved": "Y", 
  "ObjectID": "105179"
}