{
  "Medium": "Set of eight offset cards", 
  "Dimensions": "sheet (each): 7 1/16 x 7 1/16\" (18 x 18 cm)", 
  "Classification": "Print", 
  "CreditLine": "The Gilbert and Lila Silverman Fluxus Collection Gift", 
  "URL": "http://www.moma.org/collection/works/128040", 
  "ImageURL": "http://www.moma.org/media/W1siZiIsIjI2Nzk1OSJdLFsicCIsImNvbnZlcnQiLCItcmVzaXplIDIwMDB4MjAwMD4iXV0?sha=0f7b2e4c4d2c8c41", 
  "Artist": "George Brecht", 
  "Date": "c. 1964", 
  "Department": "Prints & Illustrated Books", 
  "Title": "Iced Dice", 
  "MoMANumber": "2097.2008.a-h", 
  "DateAcquired": "2008-10-08", 
  "ArtistBio": "(American, 1926\u20132008)", 
  "CuratorApproved": "Y", 
  "ObjectID": "128040"
}