{
  "Medium": "Oil and casein on canvas strips stretched over armature", 
  "Dimensions": "45 3/4 x 35 1/8\" (116.2 x 89.1 cm)", 
  "Classification": "Painting", 
  "Artist": "Salvatore Scarpitta", 
  "URL": "http://www.moma.org/collection/works/80091", 
  "CreditLine": "Gift of William Rubin", 
  "DateAcquired": "1959-04-22", 
  "Keywords": [
    "Salvatore Scarpitta", 
    "Composition", 
    "I", 
    "1959"
  ], 
  "ArtistID": 5199, 
  "Title": "Composition, I", 
  "Department": "Painting & Sculpture", 
  "MoMANumber": "615.1959", 
  "Date": "1959", 
  "ArtistBio": "(American, 1919\u20132007)", 
  "CuratorApproved": "Y", 
  "ObjectID": "80091"
}