{
  "Medium": "Pencil, charcoal, and colored pencil on tracing paper", 
  "Dimensions": "21 1/2 x 24 13/16\" (54.6 x 63 cm)", 
  "Classification": "A&D Mies van der Rohe Archive", 
  "CreditLine": "Mies van der Rohe Archive, gift of the architect", 
  "URL": "", 
  "ImageURL": null, 
  "Artist": "Ludwig Mies van der Rohe", 
  "Date": "1926-46", 
  "Department": "Architecture & Design", 
  "Title": "Chair Frame Detail (related to Tugendhat Chair) (Elevation sketch)", 
  "MoMANumber": "978.1974", 
  "DateAcquired": "1974-11-06", 
  "ArtistBio": "(American, born Germany. 1886\u20131969)", 
  "CuratorApproved": "N", 
  "ObjectID": "106808"
}