{
  "Medium": "Pencil on tracing paper", 
  "Dimensions": "13 7/8 x 30\" (35.2 x 76.2 cm)", 
  "Classification": "A&D Mies van der Rohe Archive", 
  "CreditLine": "Lilly Reich Collection, Mies van der Rohe Archive", 
  "URL": "", 
  "ImageURL": null, 
  "Artist": "Lilly Reich", 
  "Date": "1934", 
  "Department": "Architecture & Design", 
  "Title": "German People - German Work Exhibit, Berlin, Germany, Domestic-porcelain and earthenware exhibit. Plan.", 
  "MoMANumber": "R1.53", 
  "DateAcquired": "", 
  "ArtistBio": "(German, 1885\u20131947)", 
  "CuratorApproved": "N", 
  "ObjectID": "139751"
}