{
  "Medium": "Greek marble on wood and painted steel base", 
  "Dimensions": "22 3/4 x 8 1/2 x 4 3/4\" (57.8 x 21.6 x 12.1 cm)", 
  "Classification": "Sculpture", 
  "Artist": "Isamu Noguchi", 
  "URL": "http://www.moma.org/collection/works/81452", 
  "CreditLine": "In memory of Robert Carson, architect (given anonymously)", 
  "DateAcquired": "1960-11-30", 
  "Department": "Painting & Sculpture", 
  "Title": "Bird C", 
  "MoMANumber": "418.1960", 
  "Date": "1952-58", 
  "ArtistBio": "(American, 1904\u20131988)", 
  "CuratorApproved": "Y", 
  "ObjectID": "81452"
}