{
  "Medium": "Linoleum cut", 
  "Dimensions": "composition: 11 1/8 x 7 13/16\" (28.2 x 19.9 cm); sheet: 23 5/8 x 15 5/8\" (60 x 39.7 cm)", 
  "Classification": "Print", 
  "CreditLine": "Given in memory of Bertha M. Slattery", 
  "URL": "http://www.moma.org/collection/works/72506", 
  "ImageURL": "http://www.moma.org/media/W1siZiIsIjE2NDIxNCJdLFsicCIsImNvbnZlcnQiLCItcmVzaXplIDIwMDB4MjAwMD4iXV0?sha=8ac1c0de4270773b", 
  "Artist": "Henri Matisse", 
  "Date": "(1938)", 
  "Keywords": [
    "Henri Matisse", 
    "Woman", 
    "Thumb on Lips (Femme le pouce sur les l&egrave;vres)", 
    "(1938)"
  ], 
  "ArtistID": 3832, 
  "Title": "Woman, Thumb on Lips (Femme le pouce sur les l\u00e8vres)", 
  "Department": "Prints & Illustrated Books", 
  "MoMANumber": "647.1959", 
  "DateAcquired": "1959-04-22", 
  "ArtistBio": "(French, 1869\u20131954)", 
  "CuratorApproved": "Y", 
  "ObjectID": "72506"
}