{
  "Medium": "File cabinet drawer, containing objects in various media", 
  "Dimensions": "", 
  "Classification": "(not assigned)", 
  "Artist": "George Maciunas, Albert M. Fine", 
  "URL": "", 
  "CreditLine": "The Gilbert and Lila Silverman Fluxus Collection Gift", 
  "DateAcquired": "2008-10-08", 
  "Department": "Fluxus Collection", 
  "Title": "Drawer 413 / 383", 
  "MoMANumber": "FC4522", 
  "Date": "", 
  "ArtistBio": "(American, born Lithuania. 1931\u20131978) (American, 1932\u20131987)", 
  "CuratorApproved": "N", 
  "ObjectID": "139431"
}