{
  "Medium": "Oil, metallic paint and charcoal on canvas, with neon fixture and rock", 
  "Dimensions": "Overall 11' 8 1/2\" x 14' 3/4\" (356.9 x 428.6 cm)", 
  "Classification": "Painting", 
  "Artist": "Mario Merz", 
  "URL": "http://www.moma.org/collection/works/79673", 
  "CuratorApproved": "Y", 
  "CreditLine": "Anne and Sid Bass Fund", 
  "Date": "1979", 
  "ArtistID": 3941, 
  "Keywords": [
    "online art collection", 
    "Mario Merz", 
    "Fall of the House of Usher", 
    "1979"
  ], 
  "Department": "Painting & Sculpture", 
  "MoMANumber": "423.1981.a-e", 
  "ArtistBio": "(Italian, 1925\u20132003)", 
  "DateAcquired": "1981-11-17", 
  "\ufeffTitle": "Fall of the House of Usher", 
  "ObjectID": "79673"
}