{
  "Medium": "Illustrated book with eight drypoint and etchings, and one lithograph", 
  "Dimensions": "page (each approx.): 13 3/4 x 11 1/4\" (35 x 28.5 cm); overall: 14 3/16 x 11 13/16 x 7/8\" (36 x 30 x 2.3 cm)", 
  "Classification": "Illustrated Book", 
  "Artist": "Max Pechstein", 
  "URL": "http://www.moma.org/collection/works/32134", 
  "CuratorApproved": "Y", 
  "Title": "Yali und sein weisses Weib (Yali and His White Wife)", 
  "DateAcquired": "1970-03-05", 
  "Date": "1923", 
  "Department": "Prints & Illustrated Books", 
  "MoMANumber": "1193.1969.1-9", 
  "ArtistBio": "German, 1881\u20131955", 
  "CreditLine": "Gift of Mrs. Alfred Marrow", 
  "ObjectID": "32134"
}