{
  "Medium": "Gelatin silver print", 
  "Dimensions": "7 11/16 x 9 11/16\" (19.6 x 24.6 cm)", 
  "Classification": "Photograph", 
  "CreditLine": "Purchase", 
  "URL": "http://www.moma.org/collection/works/52607", 
  "ImageURL": "http://www.moma.org/media/W1siZiIsIjE4ODM0MiJdLFsicCIsImNvbnZlcnQiLCItcmVzaXplIDIwMDB4MjAwMD4iXV0?sha=963c6be435825b8e", 
  "Artist": "Nicholas Nixon", 
  "Date": "August 1973", 
  "Keywords": [
    "Nicholas Nixon", 
    "Mrs", 
    "Nancy Wheeler", 
    "Becky Norman", 
    "Jenny Bull", 
    "Bobby Maguire", 
    "Tennis Club of Albuquerque", 
    "August 1973"
  ], 
  "ArtistID": 4315, 
  "Title": "Mrs. Nancy Wheeler, Mrs. Becky Norman, Mrs. Jenny Bull, Mrs. Bobby Maguire, Tennis Club of Albuquerque", 
  "Department": "Photography", 
  "MoMANumber": "400.1974", 
  "DateAcquired": "1974-10-01", 
  "ArtistBio": "(American, born 1947)", 
  "CuratorApproved": "Y", 
  "ObjectID": "52607"
}