{
  "Medium": "Watercolor, gouache, and pencil on paper", 
  "Dimensions": "21 1/2 x 21 7/8\" (54.4 x 55.5 cm)", 
  "Classification": "Drawing", 
  "Artist": "Charles Burchfield", 
  "URL": "http://www.moma.org/collection/works/36500", 
  "CreditLine": "Gift of A. Conger Goodyear", 
  "DateAcquired": "1960-11-16", 
  "Keywords": [
    "Charles Burchfield", 
    "The Night Wind", 
    "1918"
  ], 
  "ArtistID": 870, 
  "Title": "The Night Wind", 
  "Department": "Drawings", 
  "MoMANumber": "359.1960", 
  "Date": "1918", 
  "ArtistBio": "(American, 1893\u20131967)", 
  "CuratorApproved": "Y", 
  "ObjectID": "36500"
}