{
  "Medium": "Pencil on tracing paper", 
  "Dimensions": "12 x 17 1/2\" (30.5 x 44.5 cm)", 
  "Classification": "A&D Architectural Drawing", 
  "CreditLine": "Gift of Young-June Kiehm", 
  "URL": "http://www.moma.org/collection/works/134549", 
  "ImageURL": null, 
  "Artist": "Seung H-Sang", 
  "Date": "1996-1997", 
  "Department": "Architecture & Design", 
  "Title": "Subaek-dang Residence, Namyangju, Korea, Preliminary plan sketch", 
  "MoMANumber": "115.2010", 
  "DateAcquired": "2010-03-10", 
  "ArtistBio": "(Korean, born 1952)", 
  "CuratorApproved": "Y", 
  "ObjectID": "134549"
}