{
  "Medium": "Ink and gouache on colored paper", 
  "Dimensions": "10 3/4 x 8 1/4\" (27.3 x 21 cm)", 
  "Classification": "Drawing", 
  "Artist": "Eugene Berman", 
  "URL": "http://www.moma.org/collection/works/84969", 
  "CuratorApproved": "Y", 
  "CreditLine": "Gift of Paul Magriel", 
  "Date": "(1939)", 
  "ArtistID": 502, 
  "Keywords": [
    "online art collection", 
    "Eugene Berman", 
    "Coiffures (Hairstyles)", 
    "Design for the ballet Le Diable s'amuse (Devil's Holiday)", 
    "(1939)"
  ], 
  "Department": "Drawings", 
  "MoMANumber": "59.1942.2", 
  "ArtistBio": "(American, born Russia. 1899\u20131972)", 
  "DateAcquired": "1942-03-18", 
  "\ufeffTitle": "Coiffures (Hairstyles). Design for the ballet Le Diable s'amuse (Devil's Holiday)", 
  "ObjectID": "84969"
}