{
  "Medium": "Glass, aluminum, and plastic", 
  "Dimensions": "14 x 9\" (35.5 x 22.9 cm)", 
  "Classification": "A&D Design", 
  "CreditLine": "Gift of the manufacturer", 
  "URL": "http://www.moma.org/collection/works/3385", 
  "ImageURL": "http://www.moma.org/media/W1siZiIsIjIxMjE4NSJdLFsicCIsImNvbnZlcnQiLCItcmVzaXplIDIwMDB4MjAwMD4iXV0?sha=08aae4068e97a2b3", 
  "Artist": "Van Leer Vatenfabrieken N.V., Amstelveen, The Netherlands", 
  "Date": "1949", 
  "Keywords": [
    "Van Leer Vatenfabrieken N,V,", 
    "Amstelveen", 
    "The Netherlands", 
    "Vat", 
    "1949"
  ], 
  "Title": "Vat", 
  "Department": "Architecture & Design", 
  "MoMANumber": "352.1960", 
  "DateAcquired": "1960-11-16", 
  "ArtistBio": "(Dutch)", 
  "CuratorApproved": "Y", 
  "ObjectID": "3385"
}