{
  "Medium": "Gelatin silver print", 
  "Dimensions": "7 1/16 x 9 7/16\" (18 x 24 cm)", 
  "Classification": "A&D Photograph", 
  "CreditLine": "Gift of EE Cruz & Co", 
  "URL": "http://www.moma.org/collection/works/161428", 
  "ImageURL": "http://www.moma.org/media/W1siZiIsIjI1NjEwMSJdLFsicCIsImNvbnZlcnQiLCItcmVzaXplIDIwMDB4MjAwMD4iXV0?sha=2c540c40974c2eaf", 
  "Artist": "\u00c1lvaro Siza", 
  "Date": "1971-1974", 
  "Department": "Architecture & Design", 
  "Title": "Banco Pinto & Sotto Mayor, Oliveira de Azem\u00e9is, Portugal (Interior view)", 
  "MoMANumber": "950.2012", 
  "DateAcquired": "2012-06-07", 
  "ArtistBio": "(Portuguese, born 1933)", 
  "CuratorApproved": "Y", 
  "ObjectID": "161428"
}