{
  "Medium": "Ink and colored ink on Japanese paper", 
  "Dimensions": "24 3/8 x 34 3/8\" (62.1 x 87.3 cm)", 
  "Classification": "Drawing", 
  "CreditLine": "The Joan and Lester Avnet Collection", 
  "URL": "http://www.moma.org/collection/works/34857", 
  "ImageURL": "http://www.moma.org/media/W1siZiIsIjYzODEyIl0sWyJwIiwiY29udmVydCIsIi1yZXNpemUgMjAwMHgyMDAwPiJdXQ?sha=53205e37a18be288", 
  "Artist": "Jackson Pollock", 
  "Date": "(c. 1951)", 
  "Keywords": [
    "Jackson Pollock", 
    "Untitled", 
    "(c", 
    "1951)"
  ], 
  "ArtistID": 4675, 
  "Title": "Untitled", 
  "Department": "Drawings", 
  "MoMANumber": "153.1978", 
  "DateAcquired": "1978-04-04", 
  "ArtistBio": "(American, 1912\u20131956)", 
  "CuratorApproved": "Y", 
  "ObjectID": "34857"
}