{
  "Medium": "Offset lithograph", 
  "Dimensions": "24 x 18\" (61 x 45.8 cm)", 
  "Classification": "A&D Graphic Design", 
  "Artist": "Louis Danziger", 
  "URL": "http://www.moma.org/collection/works/8085", 
  "CuratorApproved": "Y", 
  "Title": "American Paintings from The Metropolitan Museum of Art", 
  "DateAcquired": "1983-11-30", 
  "Date": "1966", 
  "Department": "Architecture & Design", 
  "MoMANumber": "766.1983", 
  "ArtistBio": "American, born 1923", 
  "CreditLine": "Gift of the designer", 
  "ObjectID": "8085"
}