{
  "Medium": "Letterpress", 
  "Dimensions": "4 7/8 x 8 3/16\" (12.5 x 20.7 cm)", 
  "Classification": "A&D Graphic Design", 
  "CreditLine": "Jan Tschichold Collection, Gift of Philip Johnson", 
  "URL": "http://www.moma.org/collection/works/8660", 
  "ImageURL": "http://www.moma.org/media/W1siZiIsIjEwNzc2Il0sWyJwIiwiY29udmVydCIsIi1yZXNpemUgMjAwMHgyMDAwPiJdXQ?sha=215c7b4a3cb50f79", 
  "Artist": "Kurt Schwitters", 
  "Date": "1923", 
  "Keywords": [
    "Kurt Schwitters", 
    "Merzmatinee", 
    "1923"
  ], 
  "ArtistID": 5293, 
  "Title": "Merzmatinee", 
  "Department": "Architecture & Design", 
  "MoMANumber": "911.1999", 
  "DateAcquired": "1999-12-10", 
  "ArtistBio": "(German, 1887\u20131948)", 
  "CuratorApproved": "Y", 
  "ObjectID": "8660"
}