{
  "Medium": "Photogravure", 
  "Dimensions": "plate: 11 5/8 x 8 11/16\" (29.5 x 22 cm); sheet: 15 7/8 x 12 11/16\" (40.4 x 32.2 cm)", 
  "Classification": "Print", 
  "CreditLine": "Acquired through the generosity of Mary M. and Sash A. Spencer", 
  "URL": "http://www.moma.org/collection/works/147147", 
  "ImageURL": "http://www.moma.org/media/W1siZiIsIjIzNDk3NSJdLFsicCIsImNvbnZlcnQiLCItcmVzaXplIDIwMDB4MjAwMD4iXV0?sha=95bd3145ecee1565", 
  "Artist": "Julian Lethbridge", 
  "Date": "2010", 
  "Department": "Prints & Illustrated Books", 
  "Title": "Alloy", 
  "MoMANumber": "296.2011", 
  "DateAcquired": "2011-05-16", 
  "ArtistBio": "(British, born 1947)", 
  "CuratorApproved": "Y", 
  "ObjectID": "147147"
}