{
  "Medium": "Woodcut", 
  "Dimensions": "composition  24 x 28 9/16\" (61 x 72.5 cm)\r\nirreg sheet  32 3/4 x 37 3/16\" (83.2 x 94.5 cm)", 
  "Classification": "Print", 
  "Artist": "Roy Lichtenstein", 
  "URL": "http://www.moma.org/collection/works/67172", 
  "CuratorApproved": "Y", 
  "CreditLine": "Blanchette Hooker Rockefeller Fund", 
  "Date": "1980", 
  "ArtistID": 3542, 
  "Keywords": [
    "online art collection", 
    "Roy Lichtenstein", 
    "American Indian Theme II", 
    "1980"
  ], 
  "Department": "Prints & Illustrated Books", 
  "MoMANumber": "336.1980", 
  "ArtistBio": "(American, 1923\u20131997)", 
  "DateAcquired": "1980-02-25", 
  "\ufeffTitle": "American Indian Theme II", 
  "ObjectID": "67172"
}