{
  "Medium": "Lithograph and raw linen, with string, polyurethane, thread and staple additions\r\n", 
  "Dimensions": "", 
  "Classification": "Print", 
  "CreditLine": "Larry Aldrich Fund and Walter Bareiss Fund", 
  "URL": "http://www.moma.org/collection/works/72126", 
  "ImageURL": "http://www.moma.org/media/W1siZiIsIjIyMDQzNSJdLFsicCIsImNvbnZlcnQiLCItcmVzaXplIDIwMDB4MjAwMD4iXV0?sha=fbf5d13665608cb3", 
  "Artist": "Christo (Christo Javacheff)", 
  "Date": "(February 22, 1971)", 
  "Keywords": [
    "Christo (Christo Javacheff)", 
    "The Whitney Museum", 
    "New York", 
    "Packed from the portfolio (Some) Not Realized Projects", 
    "(February 22", 
    "1971)"
  ], 
  "ArtistID": 1114, 
  "Title": "The Whitney Museum, New York, Packed from the portfolio (Some) Not Realized Projects", 
  "Department": "Prints & Illustrated Books", 
  "MoMANumber": "628.1971.1", 
  "DateAcquired": "1971-12-06", 
  "ArtistBio": "(American, born Bulgaria 1935)", 
  "CuratorApproved": "Y", 
  "ObjectID": "72126"
}