{
  "Medium": "Rubber stamp", 
  "Dimensions": "composition (irreg.): 26 1/4 x 10 3/4\" (66.7 x 27.3 cm); sheet: 31 1/8 x 18 13/16\" (79 x 47.8 cm)", 
  "Classification": "Print", 
  "CreditLine": "Gift of the artist in honor of the Young Print Collectors of the Department of Prints and Illustrated Books", 
  "URL": "http://www.moma.org/collection/works/69373", 
  "ImageURL": "http://www.moma.org/media/W1siZiIsIjYzODY3Il0sWyJwIiwiY29udmVydCIsIi1yZXNpemUgMjAwMHgyMDAwPiJdXQ?sha=c580198b989c594a", 
  "Artist": "Kiki Smith", 
  "Date": "1994", 
  "Keywords": [
    "Kiki Smith", 
    "Urogenitals", 
    "1994"
  ], 
  "ArtistID": 5486, 
  "Title": "Urogenitals", 
  "Department": "Prints & Illustrated Books", 
  "MoMANumber": "453.1999", 
  "DateAcquired": "1999-11-18", 
  "ArtistBio": "(American, born Germany 1954)", 
  "CuratorApproved": "Y", 
  "ObjectID": "69373"
}