{
  "Medium": "", 
  "Dimensions": "irreg. composition  1 7/16 x 2 1/2\" (3.7 x 6.3 cm)", 
  "Classification": "Illustrated Book", 
  "Artist": "Aristide Maillol", 
  "URL": "", 
  "CuratorApproved": "N", 
  "CreditLine": "The Louis E. Stern Collection", 
  "Date": "1937", 
  "Department": "Prints & Illustrated Books", 
  "MoMANumber": "903.1964.A42", 
  "ArtistBio": "(French, 1861\u20131944)", 
  "DateAcquired": "1964-10-06", 
  "\ufeffTitle": "TWO GOATS (tailpiece, page 158) from DAPHNIS AND CHLOE", 
  "ObjectID": "27643"
}