{
  "Medium": "Pencil on paper", 
  "Dimensions": "5 1/2 x 9 1/2\" (14 x 24.1 cm)", 
  "Classification": "Drawing", 
  "Artist": "Alessandro Raho", 
  "URL": "http://www.moma.org/collection/works/97136", 
  "CreditLine": "The Judith Rothschild Foundation Contemporary Drawings Collection Gift", 
  "DateAcquired": "2005-05-10", 
  "Keywords": [
    "Alessandro Raho", 
    "Catherine", 
    "2003"
  ], 
  "Title": "Catherine", 
  "Department": "Drawings", 
  "MoMANumber": "2852.2005", 
  "Date": "2003", 
  "ArtistBio": "(British, born Bahamas 1971)", 
  "CuratorApproved": "Y", 
  "ObjectID": "97136"
}