{
  "Medium": "Screenprint", 
  "Dimensions": "composition: 40 1/2 x 50 1/8\" (102.8 x 127.3 cm); sheet: 43 7/16 x 56 1/8\" (110.3 x 142.6 cm)", 
  "Classification": "Print", 
  "CreditLine": "Elizabeth Bliss Parkinson, Blanchette Hooker Rockefeller, Joanne M. Stern, and Jeanne C. Thayer Funds", 
  "URL": "http://www.moma.org/collection/works/65046", 
  "ImageURL": "http://www.moma.org/media/W1siZiIsIjIyODk2OSJdLFsicCIsImNvbnZlcnQiLCItcmVzaXplIDIwMDB4MjAwMD4iXV0?sha=2f32bca236bbb448", 
  "Artist": "Jasper Johns", 
  "Date": "1977", 
  "Keywords": [
    "Jasper Johns", 
    "The Dutch Wives", 
    "1977"
  ], 
  "ArtistID": 2923, 
  "Title": "The Dutch Wives", 
  "Department": "Prints & Illustrated Books", 
  "MoMANumber": "241.1978", 
  "DateAcquired": "1978-03-02", 
  "ArtistBio": "(American, born 1930)", 
  "CuratorApproved": "Y", 
  "ObjectID": "65046"
}