{
  "Medium": "Pencil on paper", 
  "Dimensions": "8 1/2 x 5 1/2\" (21.6 x 14 cm)", 
  "Classification": "Drawing", 
  "CreditLine": "The Judith Rothschild Foundation Contemporary Drawings Collection Gift", 
  "URL": "http://www.moma.org/collection/works/95520", 
  "ImageURL": "http://www.moma.org/media/W1siZiIsIjExMzY0MiJdLFsicCIsImNvbnZlcnQiLCItcmVzaXplIDIwMDB4MjAwMD4iXV0?sha=c13c33c8080b14c5", 
  "Artist": "Joseph Beuys", 
  "Date": "(1974)", 
  "Keywords": [
    "Joseph Beuys", 
    "Aufarbeitung des Unbew&szlig;ten zu Bewu&szlig;tem", 
    "(1974)"
  ], 
  "ArtistID": 540, 
  "Title": "Aufarbeitung des Unbew\u00dften zu Bewu\u00dftem", 
  "Department": "Drawings", 
  "MoMANumber": "1288.2005", 
  "DateAcquired": "2005-05-10", 
  "ArtistBio": "(German, 1921\u20131986)", 
  "CuratorApproved": "Y", 
  "ObjectID": "95520"
}