{
  "Medium": "Pencil on tracing paper", 
  "Dimensions": "11 3/4 x 17 1/2\" (29.8 x 44.5 cm)", 
  "Classification": "A&D Mies van der Rohe Archive", 
  "Artist": "Ludwig Mies van der Rohe", 
  "URL": "", 
  "CuratorApproved": "N", 
  "CreditLine": "Mies van der Rohe Archive, gift of the architect\r\n", 
  "Date": "1926-1927", 
  "Department": "Architecture & Design", 
  "MoMANumber": "MR4.75", 
  "ArtistBio": "(American, born Germany. 1886\u20131969)", 
  "DateAcquired": "", 
  "\ufeffTitle": "Weissenhof Apartment House, \"The Dwelling\" Exhibition, Stuttgart, Germany, Elevation", 
  "ObjectID": "107250"
}