{
  "Medium": "Etching, with pastel additions", 
  "Dimensions": "plate (irreg.): 26 x 36 15/16\" (66.1 x 93.9 cm); sheet: 28 7/16 x 38 1/2\" (72.2 x 97.8 cm)", 
  "Classification": "Print", 
  "Artist": "Alice Aycock", 
  "URL": "http://www.moma.org/collection/works/70750", 
  "CuratorApproved": "Y", 
  "CreditLine": "John B. Turner Fund", 
  "Date": "1981", 
  "ArtistID": 256, 
  "Keywords": [
    "online art collection", 
    "Alice Aycock", 
    "How To Catch and Manufacture Ghosts", 
    "1981"
  ], 
  "Department": "Prints & Illustrated Books", 
  "MoMANumber": "536.1983", 
  "ArtistBio": "(American, born 1946)", 
  "DateAcquired": "1983-05-25", 
  "\ufeffTitle": "How To Catch and Manufacture Ghosts", 
  "ObjectID": "70750"
}