{
  "Medium": "Ink on paper", 
  "Dimensions": "8 1/2 x 8 1/2\" (21.5 x 21.5 cm)", 
  "Classification": "Drawing", 
  "Artist": "Julio Gonz\u00e1lez", 
  "URL": "http://www.moma.org/collection/works/36978", 
  "CuratorApproved": "Y", 
  "CreditLine": "Gift of Roberta Gonzalez", 
  "Date": "1935", 
  "ArtistID": 2231, 
  "Keywords": [
    "online art collection", 
    "Julio Gonz&aacute;lez", 
    "Study for Head", 
    "1935"
  ], 
  "Department": "Drawings", 
  "MoMANumber": "451.1972", 
  "ArtistBio": "(Spanish, 1876\u20131942)", 
  "DateAcquired": "1972-11-02", 
  "\ufeffTitle": "Study for Head", 
  "ObjectID": "36978"
}