{
  "Medium": "Watercolor and pencil on paper", 
  "Dimensions": "80 1/4 x 48\" (203.8 x 121.9 cm)", 
  "Classification": "Drawing", 
  "Artist": "Beth Brideau", 
  "URL": "http://www.moma.org/collection/works/95622", 
  "CreditLine": "The Judith Rothschild Foundation Contemporary Drawings Collection Gift", 
  "DateAcquired": "2005-05-10", 
  "Keywords": [
    "Beth Brideau", 
    "28,000' #3", 
    "(2004)"
  ], 
  "Title": "28,000' #3", 
  "Department": "Drawings", 
  "MoMANumber": "1367.2005", 
  "Date": "(2004)", 
  "ArtistBio": "(American, born 1976)", 
  "CuratorApproved": "Y", 
  "ObjectID": "95622"
}