{
  "Medium": "Gelatin silver print, printed 1980s", 
  "Dimensions": "14 1/4 x 9 5/8\" (36.2 x 24.5 cm)", 
  "Classification": "Photograph", 
  "CreditLine": "Gift of Lee Friedlander", 
  "URL": "http://www.moma.org/collection/works/142315", 
  "ImageURL": "http://www.moma.org/media/W1siZiIsIjIxODU1MyJdLFsicCIsImNvbnZlcnQiLCItcmVzaXplIDIwMDB4MjAwMD4iXV0?sha=eb40d4d96075f53c", 
  "Artist": "Henri Cartier-Bresson", 
  "Date": "1975", 
  "Department": "Photography", 
  "Title": "Castile, Spain", 
  "MoMANumber": "407.2011", 
  "DateAcquired": "2011-05-18", 
  "ArtistBio": "(French, 1908\u20132004)", 
  "CuratorApproved": "Y", 
  "ObjectID": "142315"
}