{
  "Medium": "Offset lithograph", 
  "Dimensions": "31 7/8 x 22 1/2\" (81 x 57.2 cm)", 
  "Classification": "A&D Graphic Design", 
  "Artist": "Franciszek Starowieyski", 
  "URL": "http://www.moma.org/collection/works/6946", 
  "CuratorApproved": "Y", 
  "Title": "Trzema Krzyzykami", 
  "DateAcquired": "1985-11-18", 
  "Date": "1978", 
  "Department": "Architecture & Design", 
  "MoMANumber": "438.1985", 
  "ArtistBio": "Polish, 1930\u20132009", 
  "CreditLine": "Poster Fund", 
  "ObjectID": "6946"
}