{
  "Medium": "Woodcut, printed in color", 
  "Dimensions": "composition  10 15/16 x 2 1/2\" (27.8 x 6.3 cm)", 
  "Classification": "Illustrated Book", 
  "Artist": "Antonio Frasconi", 
  "URL": "", 
  "CuratorApproved": "N", 
  "Title": "In-text plate (folio 8) from IN MEMORIAN: PIER PAOLO PASOLINI, UNA DISPERATA VITALIT\u00c1", 
  "DateAcquired": "1994-01-25", 
  "Date": "1993", 
  "Department": "Prints & Illustrated Books", 
  "MoMANumber": "179.1994.3", 
  "ArtistBio": "American, born Argentina. 1919\u20132013", 
  "CreditLine": "The Philip and Lynn Straus Foundation Fund", 
  "ObjectID": "12858"
}