{
  "Medium": "Charcoal and oil on paper", 
  "Dimensions": "23 x 15\" (58.4 x 38.1 cm)", 
  "Classification": "Drawing", 
  "Artist": "Peter Doig", 
  "URL": "http://www.moma.org/collection/works/95824", 
  "CuratorApproved": "Y", 
  "CreditLine": "The Judith Rothschild Foundation Contemporary Drawings Collection Gift", 
  "Date": "2003", 
  "ArtistID": 8087, 
  "Keywords": [
    "online art collection", 
    "Peter Doig", 
    "Pelican", 
    "2003"
  ], 
  "Department": "Drawings", 
  "MoMANumber": "1572.2005", 
  "ArtistBio": "(British, born 1959)", 
  "DateAcquired": "2005-05-10", 
  "\ufeffTitle": "Pelican", 
  "ObjectID": "95824"
}