{
  "Medium": "Lithograph", 
  "Dimensions": "28 x 39\" (71.1 x 99.1 cm)", 
  "Classification": "A&D Graphic Design", 
  "CreditLine": "Gift of Lawrence Benenson", 
  "URL": "http://www.moma.org/collection/works/156140", 
  "ImageURL": "http://www.moma.org/media/W1siZiIsIjI3MTc0NyJdLFsicCIsImNvbnZlcnQiLCItcmVzaXplIDIwMDB4MjAwMD4iXV0?sha=07a0a7b55a439e10", 
  "Artist": "Unknown Designer", 
  "Date": "1977", 
  "Department": "Architecture & Design", 
  "Title": "Sex Pistols, Pretty Vacant, Dance to the Sex Pistols", 
  "MoMANumber": "222.2012", 
  "DateAcquired": "2012-02-09", 
  "ArtistBio": "(Nationality unknown)", 
  "CuratorApproved": "Y", 
  "ObjectID": "156140"
}