{
  "Medium": "Gouache and pencil on paper", 
  "Dimensions": "6 x 6\" (15.3 x 15.3 cm)", 
  "Classification": "Drawing", 
  "Artist": "Jo Baer", 
  "URL": "http://www.moma.org/collection/works/36551", 
  "CuratorApproved": "Y", 
  "CreditLine": "Gift of Sarah-Ann and Werner H. Kramarsky", 
  "Date": "1962", 
  "ArtistID": 281, 
  "Keywords": [
    "online art collection", 
    "Jo Baer", 
    "Rook", 
    "1962"
  ], 
  "Department": "Drawings", 
  "MoMANumber": "372.1999", 
  "ArtistBio": "(American, born 1929)", 
  "DateAcquired": "1999-10-21", 
  "\ufeffTitle": "Rook", 
  "ObjectID": "36551"
}