{
  "Medium": "Resin, cotton string, and felt-tipped pen", 
  "Dimensions": "93 x 64 x 64\" (236.2 x 162.6 x 162.6 cm) Scale 1:100", 
  "Classification": "A&D Architectural Model", 
  "Artist": "Ole Scheeren, Rem Koolhaas", 
  "URL": "http://www.moma.org/collection/works/91577", 
  "CuratorApproved": "Y", 
  "CreditLine": "Gift of Elise Jaffe + Jeffrey Brown", 
  "Date": "2002-", 
  "Keywords": [
    "online art collection", 
    "Ole Scheeren and Rem Koolhaas", 
    "Central Chinese Television Tower (CCTV)", 
    "Beijing", 
    "China", 
    "2002-"
  ], 
  "Department": "Architecture & Design", 
  "MoMANumber": "488.2004", 
  "ArtistBio": "(German, born 1971) (Dutch, born 1944)", 
  "DateAcquired": "2004-10-14", 
  "\ufeffTitle": "Central Chinese Television Tower (CCTV), Beijing, China", 
  "ObjectID": "91577"
}