{
  "Medium": "Lithograph, offset printed", 
  "Dimensions": "sheet: 18 1/2 x 12 3/8\" (47 x 31.5 cm)", 
  "Classification": "Print", 
  "Artist": "Peter Weibel, Cathrin Pichler, Otto E. Rossler", 
  "URL": "", 
  "CreditLine": "Linda Barth Goldstein Fund", 
  "DateAcquired": "2006-06-01", 
  "Department": "Prints & Illustrated Books", 
  "Title": "Untitled for the Museum in Progress project Symposia: Art and Science", 
  "MoMANumber": "514.2006.92", 
  "Date": "(newspaper published: March 13, 1999)", 
  "ArtistBio": "(Ukranian, born 1944) (German, born 1940)", 
  "CuratorApproved": "N", 
  "ObjectID": "103793"
}