{
  "Medium": "Pewter", 
  "Dimensions": ".a (body): 4 1/2 x 9 x 7 1/2\" (11.4 x 22.9 x 19 cm)  .b (lid): 1 9/16 x 5 3/8\" (3.9 x 13.7 cm)", 
  "Classification": "A&D Design", 
  "Artist": "Hermann Fauser", 
  "URL": "http://www.moma.org/collection/works/2622", 
  "CuratorApproved": "Y", 
  "Title": "Biscuit Box", 
  "DateAcquired": "1987-05-27", 
  "Date": "1902-04", 
  "Department": "Architecture & Design", 
  "MoMANumber": "201.1987.a-b", 
  "ArtistBio": "German, 1874\u20131947", 
  "CreditLine": "Est\u00e9e and Joseph Lauder Design Fund", 
  "ObjectID": "2622"
}