{
  "Medium": "One from a portfolio of 12 digital prints", 
  "Dimensions": "composition: 11 x 19\" (27.9 x 48.2 cm); sheet: 16 15/16 x 21 7/8\" (43 x 55.5 cm)", 
  "Classification": "Print", 
  "CreditLine": "Fund for the Twenty-First Century", 
  "URL": "http://www.moma.org/collection/works/147632", 
  "ImageURL": "http://www.moma.org/media/W1siZiIsIjIxNTk3MyJdLFsicCIsImNvbnZlcnQiLCItcmVzaXplIDIwMDB4MjAwMD4iXV0?sha=81f863dd67653948", 
  "Artist": "Seher Shah", 
  "Date": "2007", 
  "Department": "Prints & Illustrated Books", 
  "Title": "Untitled from The Black Star", 
  "MoMANumber": "601.2008.6", 
  "DateAcquired": "2008-06-18", 
  "ArtistBio": "(Pakistani, born 1975)", 
  "CuratorApproved": "Y", 
  "ObjectID": "147632"
}