{
  "Medium": "Series of seven lithographs", 
  "Dimensions": "Various composition dimensions.  Sheet (ea. approx.):  24 15/16 x 19\" (63.3 x 48.2 cm)", 
  "Classification": "Print", 
  "CreditLine": "John B. Turner Fund", 
  "URL": "http://www.moma.org/collection/works/59735", 
  "ImageURL": null, 
  "Artist": "Gerald Gooch", 
  "Date": "1968", 
  "Keywords": [
    "Gerald Gooch", 
    "My Cup Runneth Over", 
    "1968"
  ], 
  "ArtistID": 2234, 
  "Title": "My Cup Runneth Over", 
  "Department": "Prints & Illustrated Books", 
  "MoMANumber": "8.1972.1-7", 
  "DateAcquired": "1972-02-07", 
  "ArtistBio": "(American, born 1933)", 
  "CuratorApproved": "Y", 
  "ObjectID": "59735"
}