{
  "Medium": "Chromogenic color print", 
  "Dimensions": "15 1/8 x 22 7/8\" (38.5 x 58.1 cm)", 
  "Classification": "Photograph", 
  "Artist": "Philip-Lorca diCorcia", 
  "URL": "http://www.moma.org/collection/works/57854", 
  "CreditLine": "Gift of Carol and Arthur Goldberg", 
  "DateAcquired": "2001-04-12", 
  "Keywords": [
    "Philip-Lorca diCorcia", 
    "Edward Earle Windsor; 20 years old; Atlanta", 
    "Georgia; $30", 
    "1990-92"
  ], 
  "ArtistID": 7027, 
  "Title": "Edward Earle Windsor; 20 years old; Atlanta, Georgia; $30", 
  "Department": "Photography", 
  "MoMANumber": "1196.2001.x1-x2", 
  "Date": "1990-92", 
  "ArtistBio": "(American, born 1951)", 
  "CuratorApproved": "Y", 
  "ObjectID": "57854"
}