{
  "Medium": "Photolithograph, printed in color, with watercolor, pencil, colored crayon, ballpoint pen, and felt tip pen additions", 
  "Dimensions": "irreg. composition  11 1/8 x 16 7/8\" (28.2 x 42.9 cm)\r\nsheet  13 1/8 x 19 11/16\" (33 x 50 cm)", 
  "Classification": "Illustrated Book", 
  "Artist": "Jean Tinguely", 
  "URL": "", 
  "CuratorApproved": "N", 
  "CreditLine": "Purchase", 
  "Date": "1970-1972", 
  "Department": "Prints & Illustrated Books", 
  "MoMANumber": "282.1974.10", 
  "ArtistBio": "(Swiss, 1925\u20131991)", 
  "DateAcquired": "1974-04-23", 
  "\ufeffTitle": "Plate (folio 11) from LA VITTORIA", 
  "ObjectID": "14546"
}