{
  "Medium": "Synthetic polymer paint on canvas", 
  "Dimensions": "6' 8\" x 7' 5\" (202.8 x 225.6 cm)", 
  "Classification": "Painting", 
  "CreditLine": "The Riklis Collection of McCrory Corporation", 
  "URL": "http://www.moma.org/collection/works/80505", 
  "ImageURL": "http://www.moma.org/media/W1siZiIsIjE1MDk0OCJdLFsicCIsImNvbnZlcnQiLCItcmVzaXplIDIwMDB4MjAwMD4iXV0?sha=e0fab17049afe869", 
  "Artist": "Robert Mangold", 
  "Date": "1972", 
  "Keywords": [
    "Robert Mangold", 
    "Distorted Circle within a Polygon I", 
    "1972"
  ], 
  "ArtistID": 3723, 
  "Title": "Distorted Circle within a Polygon I", 
  "Department": "Painting & Sculpture", 
  "MoMANumber": "1042.1983", 
  "DateAcquired": "1985-10-25", 
  "ArtistBio": "(American, born 1937)", 
  "CuratorApproved": "Y", 
  "ObjectID": "80505"
}