{
  "Medium": "Etching", 
  "Dimensions": "plate: 6 15/16 x 3\" (17.6 x 7.7 cm); sheet (irreg.): 9 7/8 x 6 11/16\" (25 x 17 cm)", 
  "Classification": "Print", 
  "Artist": "Louise Bourgeois", 
  "URL": "", 
  "CuratorApproved": "Y", 
  "Title": "Pendus Fragile (Delicate Hanging), state I", 
  "DateAcquired": "1990-05-02", 
  "Date": "(c. 1948)", 
  "Department": "Prints & Illustrated Books", 
  "MoMANumber": "151.1990.1", 
  "ArtistBio": "American, born France. 1911\u20132010", 
  "CreditLine": "Gift of the artist", 
  "ObjectID": "62990"
}