{
  "Medium": "Silver-plated and oxidized silver-plated brass", 
  "Dimensions": "Tallest piece: h. 4\" (10.2 cm)  Case: 2 5/8 x 21 1/4 x 16 1/2\" (6.7 x 54 x 41.9 cm)", 
  "Classification": "A&D Design", 
  "Artist": "Man Ray", 
  "URL": "http://www.moma.org/collection/works/2807", 
  "CuratorApproved": "Y", 
  "Title": "Chess Set", 
  "DateAcquired": "1950-06-08", 
  "Date": "1920-26", 
  "ArtistID": 3716, 
  "Keywords": [
    "online art collection", 
    "Man Ray", 
    "Chess Set", 
    "1920-26"
  ], 
  "Department": "Architecture & Design", 
  "MoMANumber": "224.1950.a-ff", 
  "ArtistBio": "American, 1890\u20131976", 
  "CreditLine": "Abby Aldrich Rockefeller Fund", 
  "ObjectID": "2807"
}