{
  "Medium": "Woodcut", 
  "Dimensions": "Sheet 24 1/16 x 36\" (61.1 x 91.5 cm) Comp. 21  1/2 x 22 5/16\" (54.6 x 56.7 cm)(irreg.)", 
  "Classification": "Print", 
  "Artist": "Eduardo Vilches", 
  "URL": "http://www.moma.org/collection/works/66863", 
  "CuratorApproved": "Y", 
  "Title": "Aircraft", 
  "DateAcquired": "1969-04-16", 
  "Date": "(1967)", 
  "Department": "Prints & Illustrated Books", 
  "MoMANumber": "319.1969", 
  "ArtistBio": "Chilean", 
  "CreditLine": "Inter-American Fund", 
  "ObjectID": "66863"
}