{
  "Medium": "Etching and aquatint", 
  "Dimensions": "plate  13 1/2 x 18 7/8\" (34.3 x 47.9 cm)  sheet  22 3/8 x 27 1/8\" (56.8 x 68.9 cm)", 
  "Classification": "Print", 
  "Artist": "Helen Frankenthaler", 
  "URL": "http://www.moma.org/collection/works/64793", 
  "CuratorApproved": "Y", 
  "Title": "Crete", 
  "DateAcquired": "1972-05-08", 
  "Date": "1969-72", 
  "ArtistID": 1974, 
  "Keywords": [
    "online art collection", 
    "Helen Frankenthaler", 
    "Crete", 
    "1969-72"
  ], 
  "Department": "Prints & Illustrated Books", 
  "MoMANumber": "229.1972", 
  "ArtistBio": "American, 1928\u20132011", 
  "CreditLine": "Gift of Celeste Bartos", 
  "ObjectID": "64793"
}