{
  "Medium": "Gelatin silver print", 
  "Dimensions": "7 1/4 x 9 5/8\" (18.4 x 24.4 cm)", 
  "Classification": "Photograph", 
  "CreditLine": "Gift of the Farm Security Administration", 
  "URL": "http://www.moma.org/collection/works/44803", 
  "ImageURL": "http://www.moma.org/media/W1siZiIsIjE5MDM2MyJdLFsicCIsImNvbnZlcnQiLCItcmVzaXplIDIwMDB4MjAwMD4iXV0?sha=e130a02bc2dc52d8", 
  "Artist": "Russell Lee", 
  "Date": "June 1937", 
  "Keywords": [
    "Russell Lee", 
    "Farm Family", 
    "Cutover Area", 
    "Wisconsin", 
    "c", 
    "1938"
  ], 
  "ArtistID": 3455, 
  "Title": "John Mathews, Wife, and Two Children in their Home near Black River Falls, Wisconsin, Farm Family, Cutover Area, Wisconsin", 
  "Department": "Photography", 
  "MoMANumber": "49.1941", 
  "DateAcquired": "1941-01-16", 
  "ArtistBio": "(American, 1903\u20131986)", 
  "CuratorApproved": "Y", 
  "ObjectID": "44803"
}