{
  "Medium": "Pastel on black paper", 
  "Dimensions": "17 3/4 x 11 1/2\" (45.1 x 29.2 cm)", 
  "Classification": "Drawing", 
  "Artist": "Lucas Samaras", 
  "URL": "http://www.moma.org/collection/works/97260", 
  "CreditLine": "The Judith Rothschild Foundation Contemporary Drawings Collection Gift", 
  "DateAcquired": "2005-05-10", 
  "Keywords": [
    "Lucas Samaras", 
    "Head #12", 
    "1981"
  ], 
  "ArtistID": 5134, 
  "Title": "Head #12", 
  "Department": "Drawings", 
  "MoMANumber": "2963.2005", 
  "Date": "1981", 
  "ArtistBio": "(American, born Greece 1936)", 
  "CuratorApproved": "Y", 
  "ObjectID": "97260"
}