{
  "Medium": "Intaglio on two sheets", 
  "Dimensions": "Sheet: 44 7/8 x 30 1/2\" (114 x 77.5 cm)", 
  "Classification": "Print", 
  "Artist": "Jasper Johns", 
  "URL": "", 
  "CreditLine": "Acquired through the generosity of Mary M. Spencer", 
  "DateAcquired": "2010-06-09", 
  "Department": "Prints & Illustrated Books", 
  "Title": "Fragment of a Letter", 
  "MoMANumber": "420.2010.a-b", 
  "Date": "2010", 
  "ArtistBio": "(American, born 1930)", 
  "CuratorApproved": "N", 
  "ObjectID": "137382"
}