{
  "Medium": "Graphite and color pencil on tracing paper", 
  "Dimensions": "21 x 19 7/8\" (53.3 x 50.5 cm)", 
  "Classification": "A&D Architectural Drawing", 
  "Artist": "James Stirling", 
  "URL": "http://www.moma.org/collection/works/509", 
  "CuratorApproved": "Y", 
  "Title": "Staatsgalerie Stuttgart   Stuttgart, Germany   Elevation of gallery entrance and perspective of canopy from below", 
  "DateAcquired": "1982-10-27", 
  "Date": "1978", 
  "Department": "Architecture & Design", 
  "MoMANumber": "393.1982", 
  "ArtistBio": "British, born Scotland 1926\u20131992", 
  "CreditLine": "Gift of the architect", 
  "ObjectID": "509"
}