{
  "Medium": "Lithograph, printed in color", 
  "Dimensions": "irreg. composition  6 15/16 x 4 9/16\" (17.6 x 11.6 cm)", 
  "Classification": "Illustrated Book", 
  "CreditLine": "Gift of Janet K. Ruttenberg", 
  "URL": "", 
  "ImageURL": null, 
  "Artist": "Georges Braque", 
  "Date": "1960", 
  "Department": "Prints & Illustrated Books", 
  "Title": "Plate (page 13) from LE TIR \u00c0 L'ARC", 
  "MoMANumber": "29.1973.4", 
  "DateAcquired": "1973-01-04", 
  "ArtistBio": "(French, 1882\u20131963)", 
  "CuratorApproved": "N", 
  "ObjectID": "10069"
}