{
  "Medium": "Chromogenic color print", 
  "Dimensions": "7 5/8 x 9 3/4\" (19.4 x 24.8 cm)\r\n", 
  "Classification": "Photograph", 
  "CreditLine": "Purchase", 
  "URL": "http://www.moma.org/collection/works/52742", 
  "ImageURL": "http://www.moma.org/media/W1siZiIsIjIxNjY3NiJdLFsicCIsImNvbnZlcnQiLCItcmVzaXplIDIwMDB4MjAwMD4iXV0?sha=ee14853be7009367", 
  "Artist": "Stephen Shore", 
  "Date": "1974", 
  "Keywords": [
    "Stephen Shore", 
    "Room 131", 
    "Howard Johnson's Motor Lodge", 
    "Phillipsburg", 
    "N,J", 
    "1974"
  ], 
  "ArtistID": 5409, 
  "Title": "Room 131, Howard Johnson's Motor Lodge, Phillipsburg, NJ", 
  "Department": "Photography", 
  "MoMANumber": "406.1974", 
  "DateAcquired": "1974-10-01", 
  "ArtistBio": "(American, born 1947)", 
  "CuratorApproved": "Y", 
  "ObjectID": "52742"
}