{
  "Medium": "Albumen silver print", 
  "Dimensions": "13 3/16 x 11\" (33.5 x 27.9 cm)", 
  "Classification": "Photograph", 
  "CreditLine": "Gift of Shirley C. Burden", 
  "URL": "http://www.moma.org/collection/works/50929", 
  "ImageURL": "http://www.moma.org/media/W1siZiIsIjUxMjEiXSxbInAiLCJjb252ZXJ0IiwiLXJlc2l6ZSAyMDAweDIwMDA%2BIl1d?sha=5dbde0843c628200", 
  "Artist": "Julia Margaret Cameron", 
  "Date": "c. 1867", 
  "Keywords": [
    "Julia Margaret Cameron", 
    "Untitled", 
    "c", 
    "1867"
  ], 
  "ArtistID": 932, 
  "Title": "Untitled", 
  "Department": "Photography", 
  "MoMANumber": "329.1968", 
  "DateAcquired": "1968-01-10", 
  "ArtistBio": "(British, 1815\u20131879)", 
  "CuratorApproved": "Y", 
  "ObjectID": "50929"
}