{
  "Medium": "Watercolor on paper\r\n", 
  "Dimensions": "9 1/2 x 12\" (24.1 x 30.5 cm)", 
  "Classification": "Drawing", 
  "Artist": "Suzan Frecon", 
  "URL": "http://www.moma.org/collection/works/95949", 
  "CreditLine": "The Judith Rothschild Foundation Contemporary Drawings Collection Gift", 
  "DateAcquired": "2005-05-10", 
  "Keywords": [
    "Suzan Frecon", 
    "vermilion colored areas on blue", 
    "(1999)"
  ], 
  "ArtistID": 8092, 
  "Title": "vermilion colored areas on blue", 
  "Department": "Drawings", 
  "MoMANumber": "1683.2005", 
  "Date": "(1999)", 
  "ArtistBio": "(American, born 1941)", 
  "CuratorApproved": "Y", 
  "ObjectID": "95949"
}