{
  "Medium": "Woodcut, printed in black, with die cut", 
  "Dimensions": "Composition (irreg): 3 9/16 x 4 1/8\" (9 x 10.4 cm)", 
  "Classification": "Illustrated Book", 
  "CreditLine": "Mary Ellen Meehan Fund", 
  "URL": "", 
  "ImageURL": null, 
  "Artist": "Kiki Smith", 
  "Date": "2000", 
  "Department": "Prints & Illustrated Books", 
  "Title": "Untitled (folio 12, verso) from The Vitreous Body", 
  "MoMANumber": "2543.2001.9", 
  "DateAcquired": "2001-11-13", 
  "ArtistBio": "(American, born Germany 1954)", 
  "CuratorApproved": "N", 
  "ObjectID": "86794"
}