{
  "Medium": "Felt-tippped pen on tracing paper", 
  "Dimensions": "16 3/4 x 18 3/8\" (42.5 x 46.7 cm)", 
  "Classification": "A&D Architectural Drawing", 
  "Artist": "Ricardo Bofill", 
  "URL": "http://www.moma.org/collection/works/505", 
  "CuratorApproved": "Y", 
  "CreditLine": "Gift of Ricardo Bofill Taller de Arquitectura", 
  "Date": "1979\u20131985", 
  "ArtistID": 632, 
  "Keywords": [
    "online art collection", 
    "Ricardo Bofill", 
    "Les Eschelles du Baroque Apartment Building", 
    "Paris", 
    "France", 
    "Plan study", 
    "Unknown"
  ], 
  "Department": "Architecture & Design", 
  "MoMANumber": "392.1985", 
  "ArtistBio": "(Spanish, born 1939)", 
  "DateAcquired": "1985-11-18", 
  "\ufeffTitle": "Les Eschelles du Baroque Apartment Building, Paris, France, Plan study", 
  "ObjectID": "505"
}