{
  "Medium": "Offset lithograph", 
  "Dimensions": "30 11/16 x 22 1/8\" (78 x 56.2 cm)", 
  "Classification": "A&D Graphic Design", 
  "Artist": "Robert Rauschenberg", 
  "URL": "http://www.moma.org/collection/works/7909", 
  "CuratorApproved": "Y", 
  "Title": "R. R. At Leo's - Mar. 29, 420 W. Broadway", 
  "DateAcquired": "1980-10-30", 
  "Date": "1980", 
  "Department": "Architecture & Design", 
  "MoMANumber": "677.1980", 
  "ArtistBio": "American, 1925\u20132008", 
  "CreditLine": "Gift of the Leo Castelli Gallery", 
  "ObjectID": "7909"
}