{
  "Medium": "Wood and plastic", 
  "Dimensions": "11 13/16 x 26 5/8 x 15 3/8\" (30 x 67.6 x 39.1 cm)\r\n2 5/8\" (6.7 cm)", 
  "Classification": "A&D Architectural Model", 
  "Artist": "The Group, Juha Kaakko, Ilkka Laine, Kimmo Liimatainen, Jari Tirkkonen", 
  "URL": "http://www.moma.org/collection/works/1051", 
  "CuratorApproved": "Y", 
  "CreditLine": "Gift of the architects in honor of Philip Johnson", 
  "Date": "1990-92", 
  "ArtistID": 7857, 
  "Keywords": [
    "online art collection", 
    "The Group", 
    "Juha Kaakko", 
    "Ilkka Laine", 
    "Kimmo Liimatainen and Jari Tirkkonen", 
    "Leisure Studio", 
    "Puolarmaari", 
    "Espoo", 
    "Finland", 
    "1990-92"
  ], 
  "Department": "Architecture & Design", 
  "MoMANumber": "444.1997", 
  "ArtistBio": "(Finnish) (Finnish, born 1964) (Finnish, born 1964) (Finnish, born 1965) (Finnish, born 1965)", 
  "DateAcquired": "1997-10-17", 
  "\ufeffTitle": "Leisure Studio, Puolarmaari, Espoo, Finland", 
  "ObjectID": "1051"
}