{
  "Medium": "NULL", 
  "Dimensions": "irreg. composition  15 1/4 x 23 3/4\" (38.7 x 60.3 cm)", 
  "Classification": "Illustrated Book", 
  "Artist": "Bruce McLean", 
  "URL": "", 
  "CuratorApproved": "N", 
  "Title": "Double page plate (folios 20 verso and 21) from DREAM WORK", 
  "DateAcquired": "1987-05-14", 
  "Date": "1984-1985", 
  "Department": "Prints & Illustrated Books", 
  "MoMANumber": "183.1987.16", 
  "ArtistBio": "British, born 1944", 
  "CreditLine": "NULL", 
  "ObjectID": "13081"
}