{
  "Medium": "Lithograph", 
  "Dimensions": "16 x 12\" (40.6 x 30.5 cm)", 
  "Classification": "A&D Graphic Design", 
  "CreditLine": "Gift of Lawrence Benenson", 
  "URL": "http://www.moma.org/collection/works/156028", 
  "ImageURL": "http://www.moma.org/media/W1siZiIsIjI1MjIzNSJdLFsicCIsImNvbnZlcnQiLCItcmVzaXplIDIwMDB4MjAwMD4iXV0?sha=5ef5d5feef549a67", 
  "Artist": "Unknown Designer", 
  "Date": "1977", 
  "Department": "Architecture & Design", 
  "Title": "Blitzkrieg Bop", 
  "MoMANumber": "196.2012", 
  "DateAcquired": "2012-02-09", 
  "ArtistBio": "(Nationality unknown)", 
  "CuratorApproved": "Y", 
  "ObjectID": "156028"
}