{
  "Medium": "Etching, printed in black", 
  "Dimensions": "Plate 19 7/16 x 12 1/2\" (49.4 x 31.5 cm) Sheet 26 11/16 x 20 1/2\" (67.8 x 52.1 cm)", 
  "Classification": "Print", 
  "Artist": "Johannes Gachnang", 
  "URL": "", 
  "CuratorApproved": "N", 
  "CreditLine": "", 
  "Date": "1970", 
  "Department": "Prints & Illustrated Books", 
  "MoMANumber": "632.1971.2", 
  "ArtistBio": "(Swiss)", 
  "DateAcquired": "1971-12-06", 
  "\ufeffTitle": "THE CIRCUS OF THE FORMER EMPRESS THEODORA OF BYZANTIUM", 
  "ObjectID": "72197"
}