{
  "Medium": "Gelatin silver print", 
  "Dimensions": "7 1/16 x 9 7/16\" (18 x 24 cm)", 
  "Classification": "Photograph", 
  "Artist": "Unknown photographer", 
  "URL": "", 
  "CuratorApproved": "N", 
  "CreditLine": "Purchase", 
  "Date": "September, 1915", 
  "Department": "Photography", 
  "MoMANumber": "570.1971.186", 
  "ArtistBio": "", 
  "DateAcquired": "1971-11-10", 
  "\ufeffTitle": "Cristobal Coaling Station. General view from floating crane at dock No. 14, looking north", 
  "ObjectID": "83609"
}