{
  "Medium": "Lithograph", 
  "Dimensions": "39 x 26 3/4\" (99.1 x 67.9 cm)", 
  "Classification": "A&D Graphic Design", 
  "CreditLine": "Gift of Lawrence Benenson", 
  "URL": "http://www.moma.org/collection/works/156077", 
  "ImageURL": "http://www.moma.org/media/W1siZiIsIjI3MTc5MCJdLFsicCIsImNvbnZlcnQiLCItcmVzaXplIDIwMDB4MjAwMD4iXV0?sha=5db9595741c1edc7", 
  "Artist": "Top O'Graphic, Anna Persiani", 
  "Date": "1980", 
  "Department": "Architecture & Design", 
  "Title": "Poster for No Wave Festival in Bologna", 
  "MoMANumber": "295.2012", 
  "DateAcquired": "2012-02-09", 
  "ArtistBio": "", 
  "CuratorApproved": "Y", 
  "ObjectID": "156077"
}