{
  "Medium": "Oil, black chalk, and pencil on canvas", 
  "Dimensions": "17 3/4 x 37 1/2\" (45.1 x 95.3 cm)", 
  "Classification": "Painting", 
  "Artist": "Blinky Palermo", 
  "URL": "http://www.moma.org/collection/works/79727", 
  "CreditLine": "Gift of UBS", 
  "DateAcquired": "1992-06-08", 
  "Keywords": [
    "Blinky Palermo", 
    "Untitled", 
    "1968"
  ], 
  "ArtistID": 4474, 
  "Title": "Untitled", 
  "Department": "Painting & Sculpture", 
  "MoMANumber": "309.1992", 
  "Date": "1968", 
  "ArtistBio": "(German, 1943\u20131977)", 
  "CuratorApproved": "Y", 
  "ObjectID": "79727"
}