{
  "Medium": "Letterpress", 
  "Dimensions": "NULL", 
  "Classification": "A&D Graphic Design", 
  "Artist": "Filippo Tommaso Marinetti", 
  "URL": "", 
  "CuratorApproved": "N", 
  "Title": "Four plates from \"Les Mots en libert\u00e9 futuristes\"", 
  "DateAcquired": "1977-11-28", 
  "Date": "1919", 
  "Department": "Architecture & Design", 
  "MoMANumber": "598.1977.1-4", 
  "ArtistBio": "Italian, 1876\u20131944", 
  "CreditLine": "Jan Tschichold Collection, Gift of Philip Johnson", 
  "ObjectID": "7681"
}