{
  "Medium": "Gelatin silver print", 
  "Dimensions": "9 x 13 1/2\" (22.9 x 34.2 cm)", 
  "Classification": "Photograph", 
  "Artist": "Harry Callahan", 
  "URL": "http://www.moma.org/collection/works/53412", 
  "CreditLine": "Purchase", 
  "DateAcquired": "1960-11-30", 
  "Keywords": [
    "Harry Callahan", 
    "Wabash Avenue", 
    "Chicago", 
    "1959"
  ], 
  "ArtistID": 924, 
  "Title": "Wabash Avenue, Chicago", 
  "Department": "Photography", 
  "MoMANumber": "440.1960", 
  "Date": "1959", 
  "ArtistBio": "(American, 1912\u20131999)", 
  "CuratorApproved": "Y", 
  "ObjectID": "53412"
}