{
  "Medium": "Enameled steel, aluminum, and iyo-glazed rice paper", 
  "Dimensions": "52 1/2 x 12 1/4 x 5 1/2\" (133.4 x 31.1 x 14 cm)", 
  "Classification": "A&D Design", 
  "Artist": "V. Lorenzo Porcelli, Carmen Basile", 
  "URL": "http://www.moma.org/collection/works/3225", 
  "CreditLine": "Gift of the designers", 
  "DateAcquired": "1984-10-30", 
  "Keywords": [
    "V", 
    "Lorenzo Porcelli and Carmen Basile", 
    "Corona Floor Lamp", 
    "1981"
  ], 
  "ArtistID": 4697, 
  "Title": "Corona Floor Lamp", 
  "Department": "Architecture & Design", 
  "MoMANumber": "297.1984", 
  "Date": "1981", 
  "ArtistBio": "(American, born 1933) (American, born 1947)", 
  "CuratorApproved": "Y", 
  "ObjectID": "3225"
}