{
  "Medium": "Gelatin silver print", 
  "Dimensions": "4 1/2 \u00d7 3 1/2\" (11.4 \u00d7 8.9 cm)", 
  "Classification": "Photograph", 
  "Artist": "Le\u00f3n Ferrari", 
  "URL": "http://www.moma.org/collection/works/188352", 
  "CreditLine": "John Szarkowski Fund", 
  "DateAcquired": "2015-01-29", 
  "Department": "Photography", 
  "Title": "Untitled", 
  "MoMANumber": "19.2015", 
  "Date": "c. 1979", 
  "ArtistBio": "(Argentine, 1920\u20132013)", 
  "CuratorApproved": "Y", 
  "ObjectID": "188352"
}